{"database":"fakedb",
 "table":"Object",
 "is_partitioned":1,
 "chunk_id_key":"chunkId",
 "sub_chunk_id_key":"subChunkId",
 "is_director":1,
 "director_key":"objectId",
 "latitude_key":"decl",
 "longitude_key":"ra",
 "schema":[
    {"name":"objectId","type":"BIGINT NOT NULL"},

    {"name":"ra","type":"DOUBLE NOT NULL"},
    {"name":"decl","type":"DOUBLE NOT NULL"},

    {"name":"uPsFlux","type":"DOUBLE"},
    {"name":"gPsFlux","type":"DOUBLE"},
    {"name":"rPsFlux","type":"DOUBLE"},
    {"name":"iPsFlux","type":"DOUBLE"},
    {"name":"zPsFlux","type":"DOUBLE"},
    {"name":"yPsFlux","type":"DOUBLE"},
    {"name":"uPsFluxErr","type":"DOUBLE"},
    {"name":"gPsFluxErr","type":"DOUBLE"},
    {"name":"rPsFluxErr","type":"DOUBLE"},
    {"name":"iPsFluxErr","type":"DOUBLE"},
    {"name":"zPsFluxErr","type":"DOUBLE"},
    {"name":"yPsFluxErr","type":"DOUBLE"},

    {"name":"psLnL","type":"DOUBLE"},
    {"name":"psChi2","type":"DOUBLE"},
    {"name":"psN","type":"DOUBLE"},

    {"name":"uBbdRa","type":"DOUBLE"},
    {"name":"uBdRaErr","type":"DOUBLE"},
    {"name":"uBdDecl","type":"DOUBLE"},
    {"name":"uBdDeclErr","type":"DOUBLE"},
    {"name":"uBdE1","type":"DOUBLE"},
    {"name":"uBdE1Err","type":"DOUBLE"},
    {"name":"uBdE2","type":"DOUBLE"},
    {"name":"uBdE2Err","type":"DOUBLE"},
    {"name":"uBdFluxB","type":"DOUBLE"},
    {"name":"uBdFluxBErr","type":"DOUBLE"},

    {"name":"uBdFluxD","type":"DOUBLE"},
    {"name":"uBdFluxDErr","type":"DOUBLE"},
    {"name":"uBdReB","type":"DOUBLE"},
    {"name":"uBdReBErr","type":"DOUBLE"},
    {"name":"uBdReD","type":"DOUBLE"},
    {"name":"uBdReDErr","type":"DOUBLE"},
    {"name":"uBdLnL","type":"DOUBLE"},
    {"name":"uBdChi2","type":"DOUBLE"},
    {"name":"uBdN","type":"DOUBLE"},
    {"name":"gBbdRa","type":"DOUBLE"},
    {"name":"gBdRaErr","type":"DOUBLE"},
    {"name":"gBdDecl","type":"DOUBLE"},
    {"name":"gBdDeclErr","type":"DOUBLE"},
    {"name":"gBdE1","type":"DOUBLE"},
    {"name":"gBdE1Err","type":"DOUBLE"},
    {"name":"gBdE2","type":"DOUBLE"},
    {"name":"gBdE2Err","type":"DOUBLE"},
    {"name":"gBdFluxB","type":"DOUBLE"},
    {"name":"gBdFluxBErr","type":"DOUBLE"},
    {"name":"gBdFluxD","type":"DOUBLE"},
    {"name":"gBdFluxDErr","type":"DOUBLE"},
    {"name":"gBdReB","type":"DOUBLE"},
    {"name":"gBdReBErr","type":"DOUBLE"},
    {"name":"gBdReD","type":"DOUBLE"},
    {"name":"gBdReDErr","type":"DOUBLE"},
    {"name":"gBdLnL","type":"DOUBLE"},
    {"name":"gBdChi2","type":"DOUBLE"},
    {"name":"gBdN","type":"DOUBLE"},
    {"name":"rBbdRa","type":"DOUBLE"},
    {"name":"rBdRaErr","type":"DOUBLE"},
    {"name":"rBdDecl","type":"DOUBLE"},
    {"name":"rBdDeclErr","type":"DOUBLE"},
    {"name":"rBdE1","type":"DOUBLE"},
    {"name":"rBdE1Err","type":"DOUBLE"},
    {"name":"rBdE2","type":"DOUBLE"},
    {"name":"rBdE2Err","type":"DOUBLE"},
    {"name":"rBdFluxB","type":"DOUBLE"},
    {"name":"rBdFluxBErr","type":"DOUBLE"},
    {"name":"rBdFluxD","type":"DOUBLE"},
    {"name":"rBdFluxDErr","type":"DOUBLE"},
    {"name":"rBdReB","type":"DOUBLE"},
    {"name":"rBdReBErr","type":"DOUBLE"},
    {"name":"rBdReD","type":"DOUBLE"},
    {"name":"rBdReDErr","type":"DOUBLE"},
    {"name":"rBdLnL","type":"DOUBLE"},
    {"name":"rBdChi2","type":"DOUBLE"},
    {"name":"rBdN","type":"DOUBLE"},
    {"name":"iBbdRa","type":"DOUBLE"},
    {"name":"iBdRaErr","type":"DOUBLE"},
    {"name":"iBdDecl","type":"DOUBLE"},
    {"name":"iBdDeclErr","type":"DOUBLE"},
    {"name":"iBdE1","type":"DOUBLE"},
    {"name":"iBdE1Err","type":"DOUBLE"},
    {"name":"iBdE2","type":"DOUBLE"},
    {"name":"iBdE2Err","type":"DOUBLE"},
    {"name":"iBdFluxB","type":"DOUBLE"},
    {"name":"iBdFluxBErr","type":"DOUBLE"},
    {"name":"iBdFluxD","type":"DOUBLE"},
    {"name":"iBdFluxDErr","type":"DOUBLE"},
    {"name":"iBdReB","type":"DOUBLE"},
    {"name":"iBdReBErr","type":"DOUBLE"},
    {"name":"iBdReD","type":"DOUBLE"},
    {"name":"iBdReDErr","type":"DOUBLE"},
    {"name":"iBdLnL","type":"DOUBLE"},
    {"name":"iBdChi2","type":"DOUBLE"},
    {"name":"iBdN","type":"DOUBLE"},
    {"name":"zBbdRa","type":"DOUBLE"},
    {"name":"zBdRaErr","type":"DOUBLE"},
    {"name":"zBdDecl","type":"DOUBLE"},
    {"name":"zBdDeclErr","type":"DOUBLE"},
    {"name":"zBdE1","type":"DOUBLE"},
    {"name":"zBdE1Err","type":"DOUBLE"},
    {"name":"zBdE2","type":"DOUBLE"},
    {"name":"zBdE2Err","type":"DOUBLE"},
    {"name":"zBdFluxB","type":"DOUBLE"},
    {"name":"zBdFluxBErr","type":"DOUBLE"},
    {"name":"zBdFluxD","type":"DOUBLE"},
    {"name":"zBdFluxDErr","type":"DOUBLE"},
    {"name":"zBdReB","type":"DOUBLE"},
    {"name":"zBdReBErr","type":"DOUBLE"},
    {"name":"zBdReD","type":"DOUBLE"},
    {"name":"zBdReDErr","type":"DOUBLE"},
    {"name":"zBdLnL","type":"DOUBLE"},
    {"name":"zBdChi2","type":"DOUBLE"},
    {"name":"zBdN","type":"DOUBLE"},
    {"name":"yBbdRa","type":"DOUBLE"},
    {"name":"yBdRaErr","type":"DOUBLE"},
    {"name":"yBdDecl","type":"DOUBLE"},
    {"name":"yBdDeclErr","type":"DOUBLE"},
    {"name":"yBdE1","type":"DOUBLE"},
    {"name":"yBdE1Err","type":"DOUBLE"},
    {"name":"yBdE2","type":"DOUBLE"},
    {"name":"yBdE2Err","type":"DOUBLE"},
    {"name":"yBdFluxB","type":"DOUBLE"},
    {"name":"yBdFluxBErr","type":"DOUBLE"},
    {"name":"yBdFluxD","type":"DOUBLE"},
    {"name":"yBdFluxDErr","type":"DOUBLE"},
    {"name":"yBdReB","type":"DOUBLE"},
    {"name":"yBdReBErr","type":"DOUBLE"},
    {"name":"yBdReD","type":"DOUBLE"},
    {"name":"yBdReDErr","type":"DOUBLE"},
    {"name":"yBdLnL","type":"DOUBLE"},
    {"name":"yBdChi2","type":"DOUBLE"},
    {"name":"yBdN","type":"DOUBLE"},

    {"name":"ugStd","type":"DOUBLE"},
    {"name":"ugStdErr","type":"DOUBLE"},
    {"name":"grStd","type":"DOUBLE"},
    {"name":"grStdErr","type":"DOUBLE"},
    {"name":"riStd","type":"DOUBLE"},
    {"name":"riStdErr","type":"DOUBLE"},
    {"name":"izStd","type":"DOUBLE"},
    {"name":"izStdErr","type":"DOUBLE"},
    {"name":"zyStd","type":"DOUBLE"},
    {"name":"zyStdErr","type":"DOUBLE"},

    {"name":"uRa","type":"DOUBLE"},
    {"name":"uRaErr","type":"DOUBLE"},
    {"name":"uDecl","type":"DOUBLE"},
    {"name":"uDeclErr","type":"DOUBLE"},
    {"name":"gRa","type":"DOUBLE"},
    {"name":"gRaErr","type":"DOUBLE"},
    {"name":"gDecl","type":"DOUBLE"},
    {"name":"gDeclErr","type":"DOUBLE"},
    {"name":"rRa","type":"DOUBLE"},
    {"name":"rRaErr","type":"DOUBLE"},
    {"name":"rDecl","type":"DOUBLE"},
    {"name":"rDeclErr","type":"DOUBLE"},
    {"name":"iRa","type":"DOUBLE"},
    {"name":"iRaErr","type":"DOUBLE"},
    {"name":"iDecl","type":"DOUBLE"},
    {"name":"iDeclErr","type":"DOUBLE"},
    {"name":"zRa","type":"DOUBLE"},
    {"name":"zRaErr","type":"DOUBLE"},
    {"name":"zDecl","type":"DOUBLE"},
    {"name":"zDeclErr","type":"DOUBLE"},
    {"name":"yRa","type":"DOUBLE"},
    {"name":"yRaErr","type":"DOUBLE"},
    {"name":"yDecl","type":"DOUBLE"},
    {"name":"yDeclErr","type":"DOUBLE"},

    {"name":"uE1","type":"DOUBLE"},
    {"name":"uE1Err","type":"DOUBLE"},
    {"name":"uE2","type":"DOUBLE"},
    {"name":"uE2Err","type":"DOUBLE"},
    {"name":"uE1_E2_Cov","type":"DOUBLE"},
    {"name":"gE1","type":"DOUBLE"},
    {"name":"gE1Err","type":"DOUBLE"},
    {"name":"gE2","type":"DOUBLE"},
    {"name":"gE2Err","type":"DOUBLE"},
    {"name":"gE1_E2_Cov","type":"DOUBLE"},
    {"name":"rE1","type":"DOUBLE"},
    {"name":"rE1Err","type":"DOUBLE"},
    {"name":"rE2","type":"DOUBLE"},
    {"name":"rE2Err","type":"DOUBLE"},
    {"name":"rE1_E2_Cov","type":"DOUBLE"},
    {"name":"iE1","type":"DOUBLE"},
    {"name":"iE1Err","type":"DOUBLE"},
    {"name":"iE2","type":"DOUBLE"},
    {"name":"iE2Err","type":"DOUBLE"},
    {"name":"iE1_E2_Cov","type":"DOUBLE"},
    {"name":"zE1","type":"DOUBLE"},
    {"name":"zE1Err","type":"DOUBLE"},
    {"name":"zE2","type":"DOUBLE"},
    {"name":"zE2Err","type":"DOUBLE"},
    {"name":"zE1_E2_Cov","type":"DOUBLE"},
    {"name":"yE1","type":"DOUBLE"},
    {"name":"yE1Err","type":"DOUBLE"},
    {"name":"yE2","type":"DOUBLE"},
    {"name":"yE2Err","type":"DOUBLE"},
    {"name":"yE1_E2_Cov","type":"DOUBLE"},

    {"name":"uMSum","type":"DOUBLE"},
    {"name":"uMSumErr","type":"DOUBLE"},
    {"name":"gMSum","type":"DOUBLE"},
    {"name":"gMSumErr","type":"DOUBLE"},
    {"name":"rMSum","type":"DOUBLE"},
    {"name":"rMSumErr","type":"DOUBLE"},
    {"name":"iMSum","type":"DOUBLE"},
    {"name":"iMSumErr","type":"DOUBLE"},
    {"name":"zMSum","type":"DOUBLE"},
    {"name":"zMSumErr","type":"DOUBLE"},
    {"name":"yMSum","type":"DOUBLE"},
    {"name":"yMSumErr","type":"DOUBLE"},
    {"name":"uM4","type":"DOUBLE"},
    {"name":"gM4","type":"DOUBLE"},
    {"name":"rM4","type":"DOUBLE"},
    {"name":"iM4","type":"DOUBLE"},
    {"name":"zM4","type":"DOUBLE"},
    {"name":"yM4","type":"DOUBLE"},

    {"name":"uPetroRad","type":"DOUBLE"},
    {"name":"uPetroRadErr","type":"DOUBLE"},
    {"name":"gPetroRad","type":"DOUBLE"},
    {"name":"gPetroRadErr","type":"DOUBLE"},
    {"name":"rPetroRad","type":"DOUBLE"},
    {"name":"rPetroRadErr","type":"DOUBLE"},
    {"name":"iPetroRad","type":"DOUBLE"},
    {"name":"iPetroRadErr","type":"DOUBLE"},
    {"name":"zPetroRad","type":"DOUBLE"},
    {"name":"zPetroRadErr","type":"DOUBLE"},
    {"name":"yPetroRad","type":"DOUBLE"},
    {"name":"yPetroRadErr","type":"DOUBLE"},
    {"name":"petroFilter","type":"DOUBLE"},
    {"name":"uPetroFlux","type":"DOUBLE"},
    {"name":"uPetroFluxErr","type":"DOUBLE"},
    {"name":"gPetroFlux","type":"DOUBLE"},
    {"name":"gPetroFluxErr","type":"DOUBLE"},
    {"name":"rPetroFlux","type":"DOUBLE"},
    {"name":"rPetroFluxErr","type":"DOUBLE"},
    {"name":"iPetroFlux","type":"DOUBLE"},
    {"name":"iPetroFluxErr","type":"DOUBLE"},
    {"name":"zPetroFlux","type":"DOUBLE"},
    {"name":"zPetroFluxErr","type":"DOUBLE"},
    {"name":"yPetroFlux","type":"DOUBLE"},
    {"name":"yPetroFluxErr","type":"DOUBLE"},
    {"name":"uPetroRad50","type":"DOUBLE"},
    {"name":"uPetroRad50Err","type":"DOUBLE"},
    {"name":"gPetroRad50","type":"DOUBLE"},
    {"name":"gPetroRad50Err","type":"DOUBLE"},
    {"name":"rPetroRad50","type":"DOUBLE"},
    {"name":"rPetroRad50Err","type":"DOUBLE"},
    {"name":"iPetroRad50","type":"DOUBLE"},
    {"name":"iPetroRad50Err","type":"DOUBLE"},
    {"name":"zPetroRad50","type":"DOUBLE"},
    {"name":"zPetroRad50Err","type":"DOUBLE"},
    {"name":"yPetroRad50","type":"DOUBLE"},
    {"name":"yPetroRad50Err","type":"DOUBLE"},
    {"name":"uPetroRad90","type":"DOUBLE"},
    {"name":"uPetroRad90Err","type":"DOUBLE"},
    {"name":"gPetroRad90","type":"DOUBLE"},
    {"name":"gPetroRad90Err","type":"DOUBLE"},
    {"name":"rPetroRad90","type":"DOUBLE"},
    {"name":"rPetroRad90Err","type":"DOUBLE"},
    {"name":"iPetroRad90","type":"DOUBLE"},
    {"name":"iPetroRad90Err","type":"DOUBLE"},
    {"name":"zPetroRad90","type":"DOUBLE"},
    {"name":"zPetroRad90Err","type":"DOUBLE"},
    {"name":"yPetroRad90","type":"DOUBLE"},
    {"name":"yPetroRad90Err","type":"DOUBLE"},

    {"name":"uKronRad","type":"DOUBLE"},
    {"name":"uKronRadErr","type":"DOUBLE"},
    {"name":"gKronRad","type":"DOUBLE"},
    {"name":"gKronRadErr","type":"DOUBLE"},
    {"name":"rKronRad","type":"DOUBLE"},
    {"name":"rKronRadErr","type":"DOUBLE"},
    {"name":"iKronRad","type":"DOUBLE"},
    {"name":"iKronRadErr","type":"DOUBLE"},
    {"name":"zKronRad","type":"DOUBLE"},
    {"name":"zKronRadErr","type":"DOUBLE"},
    {"name":"yKronRad","type":"DOUBLE"},
    {"name":"yKronRadErr","type":"DOUBLE"},
    {"name":"kronFilter","type":"DOUBLE"},
    {"name":"uKronFlux","type":"DOUBLE"},
    {"name":"uKronFluxErr","type":"DOUBLE"},
    {"name":"gKronFlux","type":"DOUBLE"},
    {"name":"gKronFluxErr","type":"DOUBLE"},
    {"name":"rKronFlux","type":"DOUBLE"},
    {"name":"rKronFluxErr","type":"DOUBLE"},
    {"name":"iKronFlux","type":"DOUBLE"},
    {"name":"iKronFluxErr","type":"DOUBLE"},
    {"name":"zKronFlux","type":"DOUBLE"},
    {"name":"zKronFluxErr","type":"DOUBLE"},
    {"name":"yKronFlux","type":"DOUBLE"},
    {"name":"yKronFluxErr","type":"DOUBLE"},
    {"name":"uKronRad50","type":"DOUBLE"},
    {"name":"uKronRad50Err","type":"DOUBLE"},
    {"name":"gKronRad50","type":"DOUBLE"},
    {"name":"gKronRad50Err","type":"DOUBLE"},
    {"name":"rKronRad50","type":"DOUBLE"},
    {"name":"rKronRad50Err","type":"DOUBLE"},
    {"name":"iKronRad50","type":"DOUBLE"},
    {"name":"iKronRad50Err","type":"DOUBLE"},
    {"name":"zKronRad50","type":"DOUBLE"},
    {"name":"zKronRad50Err","type":"DOUBLE"},
    {"name":"yKronRad50","type":"DOUBLE"},
    {"name":"yKronRad50Err","type":"DOUBLE"},
    {"name":"uKronRad90","type":"DOUBLE"},
    {"name":"uKronRad90Err","type":"DOUBLE"},
    {"name":"gKronRad90","type":"DOUBLE"},
    {"name":"gKronRad90Err","type":"DOUBLE"},
    {"name":"rKronRad90","type":"DOUBLE"},
    {"name":"rKronRad90Err","type":"DOUBLE"},
    {"name":"iKronRad90","type":"DOUBLE"},
    {"name":"iKronRad90Err","type":"DOUBLE"},
    {"name":"zKronRad90","type":"DOUBLE"},
    {"name":"zKronRad90Err","type":"DOUBLE"},
    {"name":"yKronRad90","type":"DOUBLE"},
    {"name":"yKronRad90Err","type":"DOUBLE"},

    {"name":"uApN","type":"DOUBLE"},
    {"name":"gApN","type":"DOUBLE"},
    {"name":"rApN","type":"DOUBLE"},
    {"name":"iApN","type":"DOUBLE"},
    {"name":"zApN","type":"DOUBLE"},
    {"name":"yApN","type":"DOUBLE"},
    {"name":"extendedness","type":"DOUBLE"},
    {"name":"FLAGS1","type":"DOUBLE"},
    {"name":"FLAGS2","type":"DOUBLE"},

    {"name":"chunkId","type":"INT UNSIGNED NOT NULL"},
  {"name":"subChunkId","type":"INT UNSIGNED NOT NULL"}
 ],
 "auth_key":""
}
